nbi/__init__.py
nbi/data.py
nbi/engine.py
nbi/model.py
nbi/utils.py
nbi/nn/__init__.py
nbi/nn/flows.py
nbi/nn/resnet.py
nbi/nn/rnn.py
nbi-0.4.1.dist-info/LICENSE.txt
nbi-0.4.1.dist-info/METADATA
nbi-0.4.1.dist-info/WHEEL
nbi-0.4.1.dist-info/top_level.txt
nbi-0.4.1.dist-info/RECORD
