Metadata-Version: 2.1
Name: nbi
Version: 0.4.1
Summary: Neural Bayesian Inference
Author-email: Keming Zhang <kemingz@berkeley.edu>
Project-URL: Homepage, https://github.com/kmzzhang/nbi
Classifier: Programming Language :: Python :: 3
Classifier: License :: OSI Approved :: BSD License
Classifier: Operating System :: OS Independent
Requires-Python: >=3.7
License-File: LICENSE.txt
Requires-Dist: torch >=1.4
Requires-Dist: numpy
Requires-Dist: scipy
Requires-Dist: matplotlib
Requires-Dist: corner
Requires-Dist: joblib
Requires-Dist: pytest
Requires-Dist: tqdm
Requires-Dist: multiprocess
Requires-Dist: wandb
